pretix_fattura_elettronica-0.2.16.dist-info/METADATA
pretix_fattura_elettronica-0.2.16.dist-info/WHEEL
pretix_fattura_elettronica-0.2.16.dist-info/entry_points.txt
pretix_fattura_elettronica-0.2.16.dist-info/licenses/LICENSE
pretix_fattura_elettronica/__init__.py
pretix_fattura_elettronica/acubeapi.py
pretix_fattura_elettronica/apps.py
pretix_fattura_elettronica/enums.py
pretix_fattura_elettronica/forms.py
pretix_fattura_elettronica/locale/de/LC_MESSAGES/django.po
pretix_fattura_elettronica/locale/de_Informal/.gitkeep
pretix_fattura_elettronica/locale/de_Informal/LC_MESSAGES/django.po
pretix_fattura_elettronica/migrations/0001_initial.py
pretix_fattura_elettronica/migrations/__init__.py
pretix_fattura_elettronica/models.py
pretix_fattura_elettronica/serializers.py
pretix_fattura_elettronica/signals/__init__.py
pretix_fattura_elettronica/signals/forms.py
pretix_fattura_elettronica/signals/invoices.py
pretix_fattura_elettronica/static/pretix_fattura_elettronica/.gitkeep
pretix_fattura_elettronica/templates/pretix_fattura_elettronica/.gitkeep
pretix_fattura_elettronica/templates/pretix_fattura_elettronica/change_info.html
pretix_fattura_elettronica/templates/pretix_fattura_elettronica/einvoices.html
pretix_fattura_elettronica/templates/pretixcontrol/order/index.html
pretix_fattura_elettronica/templatetags/__init__.py
pretix_fattura_elettronica/templatetags/fatturaelt.py
pretix_fattura_elettronica/urls.py
pretix_fattura_elettronica/utils/__init__.py
pretix_fattura_elettronica/utils/normalise_unicode.py
pretix_fattura_elettronica/utils/tax.py
pretix_fattura_elettronica/views.py
pretix_fattura_elettronica-0.2.16.dist-info/RECORD
