Metadata-Version: 2.1
Name: pretix-fattura-elettronica
Version: 0.2.16
Summary: Plugin for Italian Electronic Invoices
Keywords: pretix
Author-Email: Python Italia <info@pycon.it>
Maintainer-Email: Python Italia <info@pycon.it>
License: Apache
Project-URL: homepage, https://github.com/pythonitalia/pretix-fattura-elettronica
Project-URL: repository, https://github.com/pythonitalia/pretix-fattura-elettronica
Requires-Python: >=3.8
Requires-Dist: pydantic>=2.5.1
Requires-Dist: python-codicefiscale>=0.9.0
Requires-Dist: httpx>=0.25.2
Requires-Dist: respx>=0.20.2
Requires-Dist: unidecode>=1.3.7
Provides-Extra: dev
Requires-Dist: pytest; extra == "dev"
Requires-Dist: pytest-django; extra == "dev"
Requires-Dist: django; extra == "dev"
Requires-Dist: django-rest-framework; extra == "dev"
Requires-Dist: pretix; extra == "dev"
Requires-Dist: django-countries>=7.5.1; extra == "dev"
Requires-Dist: pytest-icdiff>=0.8; extra == "dev"
Requires-Dist: time-machine>=2.14.0; extra == "dev"
Requires-Dist: devtools>=0.12.2; extra == "dev"
Requires-Dist: setuptools>=69.2.0; extra == "dev"
Requires-Dist: pdbpp>=0.10.3; extra == "dev"
Requires-Dist: inline-snapshot>=0.10.2; extra == "dev"
